swyng/__init__.py
swyng-0.0.1.dist-info/LICENSE
swyng-0.0.1.dist-info/METADATA
swyng-0.0.1.dist-info/WHEEL
swyng-0.0.1.dist-info/top_level.txt
swyng-0.0.1.dist-info/RECORD
